ragflow_sdk/__init__.py
ragflow_sdk/ragflow.py
ragflow_sdk/modules/__init__.py
ragflow_sdk/modules/agent.py
ragflow_sdk/modules/base.py
ragflow_sdk/modules/chat.py
ragflow_sdk/modules/chunk.py
ragflow_sdk/modules/dataset.py
ragflow_sdk/modules/document.py
ragflow_sdk/modules/session.py
amdperfrag_sdk-0.19.0.dist-info/METADATA
amdperfrag_sdk-0.19.0.dist-info/WHEEL
amdperfrag_sdk-0.19.0.dist-info/top_level.txt
amdperfrag_sdk-0.19.0.dist-info/RECORD
