Metadata-Version: 2.4
Name: amdperfrag-sdk
Version: 0.19.0
Summary: Python client sdk of AMD PER RAG. AMD PER RAG is an open-source RAG (Retrieval-Augmented Generation) engine based on deep document understanding.
Author-email: Zhichang Yu <yuzhichang@gmail.com>
License: Apache License, Version 2.0
Requires-Python: <3.13,>=3.10
Requires-Dist: requests<3.0.0,>=2.30.0
Requires-Dist: beartype<0.19.0,>=0.18.5
